tdms2axg/__init__.py
tdms2axg/__main__.py
tdms2axg/scripts.py
tdms2axg-0.2.0.dist-info/LICENSE
tdms2axg-0.2.0.dist-info/METADATA
tdms2axg-0.2.0.dist-info/WHEEL
tdms2axg-0.2.0.dist-info/entry_points.txt
tdms2axg-0.2.0.dist-info/top_level.txt
tdms2axg-0.2.0.dist-info/RECORD
