Metadata-Version: 2.1
Name: tdms2axg
Version: 0.2.0
Summary: A simple script for converting LabVIEW TDMS files to AxoGraph files
Home-page: https://github.com/jpgill86/tdms2axg
Author: Jeffrey Gill
Author-email: jeffrey.p.gill@gmail.com
License: MIT
Project-URL: Source code, https://github.com/jpgill86/tdms2axg
Project-URL: Bug tracker, https://github.com/jpgill86/tdms2axg/issues
Keywords: neuroscience,electrophysiology,National Instruments,LabVIEW,tdms,AxoGraph,axgx,axgd
Platform: UNKNOWN
Classifier: Programming Language :: Python :: 2
Classifier: Programming Language :: Python :: 3
Classifier: Development Status :: 3 - Alpha
Classifier: Intended Audience :: Science/Research
Classifier: Topic :: Scientific/Engineering
Classifier: License :: OSI Approved :: MIT License
Classifier: Operating System :: OS Independent
Requires-Dist: numpy
Requires-Dist: quantities
Requires-Dist: nptdms
Requires-Dist: axographio
